vibrations/__init__.py
vibrations/signals.py
vibrations/tests.py
vibrations/vibration.py
vibrations/ode/__init__.py
vibrations/ode/benchmark.py
vibrations/ode/nummerical_ode.py
vibrations-0.1a0.dist-info/DESCRIPTION.rst
vibrations-0.1a0.dist-info/METADATA
vibrations-0.1a0.dist-info/RECORD
vibrations-0.1a0.dist-info/WHEEL
vibrations-0.1a0.dist-info/metadata.json
vibrations-0.1a0.dist-info/top_level.txt
