Metadata-Version: 2.0
Name: vibrations
Version: 0.1a0
Summary: Helper functions when processing vibration data
Home-page: https://ritchievink.com
Author: Ritchie Vink
Author-email: UNKNOWN
License: MIT License
Download-URL: https://github.com/ritchie46/vibrations
Platform: UNKNOWN
Requires-Dist: numpy (>=1.11.1)
Requires-Dist: scipy (>=0.18.1)
